HTTP_db/Exceptions.py
HTTP_db/__init__.py
HTTP_db/client.py
HTTP_db-1.2.3.dist-info/METADATA
HTTP_db-1.2.3.dist-info/WHEEL
HTTP_db-1.2.3.dist-info/top_level.txt
HTTP_db-1.2.3.dist-info/RECORD
