Metadata-Version: 2.1
Name: HTTP-db
Version: 1.2.3
Summary: Simple and easy database system using HTTP
Home-page: https://github.com/nattyan-tv/HTTP_db
Author: nattyan-tv
Author-email: nananatsu2020@outlook.com
Maintainer: nattyan-tv
Maintainer-email: nananatsu2020@outlook.com
License: MIT License
Download-URL: https://github.com/nattyan-tv/HTTP_db
Keywords: HTTP,database,simple,easy,nirabot
Platform: UNKNOWN
Classifier: License :: OSI Approved :: MIT License
Classifier: Programming Language :: Python :: 3 :: Only
Requires-Python: >=3.7
Requires-Dist: aiohttp (>=3.8.1)
